{
  "parent": "rpp:renew/root",
  "criteria": {
    "has_sapling":{
      "trigger": "minecraft:inventory_changed",
      "conditions": {
        "items": [
          {
            "tag": "minecraft:saplings"
          }
        ]
      }
    },
    "has_the_recipe":{
      "trigger": "minecraft:recipe_unlocked",
      "conditions": {
        "recipe": "rpp:renew/dead_bush"
      }
    }
  },
  "requirements": [
    [
      "has_sapling",
      "has_the_recipe"
    ]
  ],
  "rewards": {
    "recipes": [
      "rpp:renew/dead_bush"
    ]
  }
}