{
  "parent": "rpp:renewability/root",
  "criteria": {
    "has_tuff": {
      "trigger": "minecraft:inventory_changed",
      "conditions": {
        "items": [
          {
            "items": [
              "minecraft:tuff"
            ]
          }
        ]
      }
    },
    "has_the_recipe": {
      "trigger": "minecraft:recipe_unlocked",
      "conditions": {
        "recipe": "rpp:renewability/stone/deepslate"
      }
    }
  },
  "requirements": [
    [
      "has_tuff",
      "has_the_recipe"
    ]
  ],
  "rewards": {
    "recipes": [
      "rpp:renewability/stone/deepslate"
    ]
  }
}